<?xml version="1.0" encoding="UTF-8"?>
<fiche>
  <video>
    <title>Jeunes vulnérables : déviance et parcours de vie</title>
    <visibility>unlisted</visibility>
    <date>2024-05-23</date>
    <description><![CDATA[L’unité recherche et études du service de la recherche et de la documentation (SRD) en<br>coopération avec le pôle Interventions Éducatives (PIE) du service de la formation (SF) de<br>l’École nationale de protection judiciaire de la jeunesse (ENPJJ) organise une journée d’études<br>destinée à diffuser des résultats de recherches dans le champ de la sociologie des parcours de<br>vie et des dynamiques sociales.]]></description>
  </video>
  <event>
    <title>Jeunes vulnérables : déviance et parcours de vie</title>
    <subtitle>Bienvenue</subtitle>
    <style>enpjj</style>
    <location>Amphi Condorcet Bas</location>
    <onsite>100</onsite>
    <remote>50</remote>
    <release>Synchrone</release>
    <date>2024-05-23</date>
    <start>09:00</start>
  </event>
  <speaker>
    <SP1>
      <id>2826</id>
      <name>Hélène CHÉRONNET</name>
      <function><![CDATA[Chercheure en sociologie, HDR, ENPJJ,<br>Centre lillois d’études et de recherches sociologiques et économiques (Clersé),<br>Université de LILLE]]></function>
      <translation/>
      <attendance>onsite</attendance>
      <link>Copier/coller le lien ici...</link>
    </SP1>
    <SP2>
      <id>2136</id>
      <name>Delphine BRUGGEMAN</name>
      <function>Responsable de l’unité recherche et études, SRD, ENPJJ</function>
      <translation/>
      <attendance>onsite</attendance>
      <link>Copier/coller le lien ici...</link>
    </SP2>
    <SP3>
      <id>9158</id>
      <name>Cécile LALUMIÈRE</name>
      <function>Directrice du service de la formation, ENPJJ</function>
      <translation/>
      <attendance>onsite</attendance>
      <link>Copier/coller le lien ici...</link>
    </SP3>
    <SP4>
      <id>2879</id>
      <name>Benjamin DENECHEAU</name>
      <function><![CDATA[Maître de conférences en sciences de l’éducation,<br>Université Paris-Est Créteil, LIRTES]]></function>
      <translation/>
      <attendance>onsite</attendance>
      <link>Copier/coller le lien ici...</link>
    </SP4>
    <SP5>
      <id>0522</id>
      <name>Laurent SOLINI</name>
      <function><![CDATA[Maître de conférences en sociologie,<br>Université de Montpellier, laboratoire Santesih]]></function>
      <translation/>
      <attendance>onsite</attendance>
      <link>Copier/coller le lien ici...</link>
    </SP5>
    <SP6>
      <id>1803</id>
      <name>Andréa LAURET</name>
      <function><![CDATA[Éducatrice, <br>Service éducatif auprès du tribunal (SEAT), <br>Bobigny]]></function>
      <translation/>
      <attendance>onsite</attendance>
      <link>Copier/coller le lien ici...</link>
    </SP6>
    <SP7>
      <id>1564</id>
      <name>Laura DELCOURT</name>
      <function><![CDATA[Docteure en sociologie, <br>CeRIES, Université de Lille, <br>Ingénieure de Recherche, Laboratoire CEJESCO, Université de Reims]]></function>
      <translation/>
      <attendance>onsite</attendance>
      <link>Copier/coller le lien ici...</link>
    </SP7>
    <SP8>
      <id>7912</id>
      <name>Guillaume TEILLET</name>
      <function><![CDATA[Maître de conférences en sociologie, <br>Université de Poitiers, laboratoire Gresco]]></function>
      <translation/>
      <attendance>onsite</attendance>
      <link>Copier/coller le lien ici...</link>
    </SP8>
    <SP9>
      <id>8629</id>
      <name>Léa CROIZET</name>
      <function><![CDATA[Doctorante en sociologie,<br>Ingénieure d’études au Gresco]]></function>
      <translation/>
      <attendance>onsite</attendance>
      <link>Copier/coller le lien ici...</link>
    </SP9>
    <SP10>
      <id>3335</id>
      <name>Isabelle LACROIX</name>
      <function><![CDATA[Maîtresse de conférences en sociologie, <br>Printemps-UVSQ/Paris-Saclay]]></function>
      <translation/>
      <attendance>onsite</attendance>
      <link>Copier/coller le lien ici...</link>
    </SP10>
    <SP11>
      <id>8879</id>
      <name>Yaëlle AMSELLEM-MAINGUY</name>
      <function><![CDATA[Chargée de recherche<br>Institut national de la jeunesse et de l’éducation populaire,<br>(ISP - ENS Paris Saclay), associée au CERLIS]]></function>
      <translation/>
      <attendance>onsite</attendance>
      <link>Copier/coller le lien ici...</link>
    </SP11>
    <SP12>
      <id>5236</id>
      <name>Alice SIMON</name>
      <function><![CDATA[Responsable de la recherche DPJJ, <br>Docteure en sociologie]]></function>
      <translation/>
      <attendance>onsite</attendance>
      <link>Copier/coller le lien ici...</link>
    </SP12>
    <SP13>
      <id>4600</id>
      <name>María EUGENIA LONGO</name>
      <function><![CDATA[Professeure titulaire à l’Institut national de la recherche scientifique (INRS), <br>]]></function>
      <translation><![CDATA[Cotitulaire de la Chaire-réseau de recherche sur la jeunesse<br>Québec (Canada)]]></translation>
      <attendance>remote</attendance>
      <link>Copier/coller le lien ici...</link>
    </SP13>
  </speaker>
  <sequence>
    <SQ1>
      <id>9845</id>
      <type>transition</type>
      <html><![CDATA[<h1>Ouverture institutionnelle</h1>]]></html>
    </SQ1>
    <SQ2>
      <id>5540</id>
      <type>speech</type>
      <duration>15</duration>
      <needs>pupitre</needs>
      <speaking>9158,2136</speaking>
      <extra>
        <ddr>
          <checked>false</checked>
          <sources>Indiquer ici le détail des médias à diffuser.</sources>
        </ddr>
        <scroll>
          <checked>false</checked>
          <message>Indiquer ici le message à faire défiler (numéro de téléphone, consigne de sécurité, appel à l’action, etc.).</message>
        </scroll>
        <requests>
          <checked>false</checked>
          <specifications>Préciser ici vos besoins techniques spécifiques.</specifications>
        </requests>
      </extra>
    </SQ2>
    <SQ3>
      <id>1185</id>
      <type>transition</type>
      <html><![CDATA[<h1>Conférence introductive :<br>Au-delà de la « carrière » déviante,<br>la pertinence de l’analyse des parcours de viede jeunes<br>en situation de délinquance</h1>]]></html>
    </SQ3>
    <SQ4>
      <id>3534</id>
      <type>speech</type>
      <duration>30</duration>
      <needs>bureau</needs>
      <speaking>2826</speaking>
      <extra>
        <ddr>
          <checked>false</checked>
          <sources>Indiquer ici le détail des médias à diffuser.</sources>
        </ddr>
        <scroll>
          <checked>false</checked>
          <message>Indiquer ici le message à faire défiler (numéro de téléphone, consigne de sécurité, appel à l’action, etc.).</message>
        </scroll>
        <requests>
          <checked>false</checked>
          <specifications>Préciser ici vos besoins techniques spécifiques.</specifications>
        </requests>
      </extra>
    </SQ4>
    <SQ5>
      <id>8926</id>
      <type>transition</type>
      <html><![CDATA[<h1>Modalités de socialisation et d’affiliation :<br><br>Parcours scolaires des jeunes sous main de justice :<br>à l’épreuve des marges de l’école</h1>]]></html>
    </SQ5>
    <SQ6>
      <id>6530</id>
      <type>speech</type>
      <duration>20</duration>
      <needs>bureau</needs>
      <speaking>2136,2879</speaking>
      <extra>
        <ddr>
          <checked>false</checked>
          <sources>Indiquer ici le détail des médias à diffuser.</sources>
        </ddr>
        <scroll>
          <checked>false</checked>
          <message>Indiquer ici le message à faire défiler (numéro de téléphone, consigne de sécurité, appel à l’action, etc.).</message>
        </scroll>
        <requests>
          <checked>false</checked>
          <specifications>Préciser ici vos besoins techniques spécifiques.</specifications>
        </requests>
      </extra>
    </SQ6>
    <SQ7>
      <id>3924</id>
      <type>transition</type>
      <html><![CDATA[<h1>Modalités de socialisation et d’affiliation :<br><br>Jeunesse délinquante et violence symbolique.<br>Les placements et déplacements de justice<br>comme des injonctions sourdes</h1>]]></html>
    </SQ7>
    <SQ8>
      <id>9100</id>
      <type>speech</type>
      <duration>20</duration>
      <needs>bureau</needs>
      <speaking>2136,0522</speaking>
      <extra>
        <ddr>
          <checked>false</checked>
          <sources>Indiquer ici le détail des médias à diffuser.</sources>
        </ddr>
        <scroll>
          <checked>false</checked>
          <message>Indiquer ici le message à faire défiler (numéro de téléphone, consigne de sécurité, appel à l’action, etc.).</message>
        </scroll>
        <requests>
          <checked>false</checked>
          <specifications>Préciser ici vos besoins techniques spécifiques.</specifications>
        </requests>
      </extra>
    </SQ8>
    <SQ9>
      <id>5659</id>
      <type>transition</type>
      <html><![CDATA[<h1>Modalités de socialisation et d’affiliation :<br><br>Convertir les compétences développées<br>au cours de la carrière délinquante<br>en qualités professionnelles attendues<br>dans le monde légal, un levier pour la désistance</h1>]]></html>
    </SQ9>
    <SQ10>
      <id>9923</id>
      <type>speech</type>
      <duration>35</duration>
      <needs/>
      <speaking>2136,1803</speaking>
      <extra>
        <ddr>
          <checked>false</checked>
          <sources>Indiquer ici le détail des médias à diffuser.</sources>
        </ddr>
        <scroll>
          <checked>false</checked>
          <message>Indiquer ici le message à faire défiler (numéro de téléphone, consigne de sécurité, appel à l’action, etc.).</message>
        </scroll>
        <requests>
          <checked>false</checked>
          <specifications>Préciser ici vos besoins techniques spécifiques.</specifications>
        </requests>
      </extra>
    </SQ10>
    <SQ11>
      <id>1210</id>
      <type>pause</type>
      <duration>15</duration>
    </SQ11>
    <SQ12>
      <id>7879</id>
      <type>transition</type>
      <html><![CDATA[<h1>Parcours et expériences variées de la pénalité :<br><br>D’une étiquette à l’autre.<br>Des jeunesses populaires entre pénal et handicap</h1>]]></html>
    </SQ12>
    <SQ13>
      <id>1808</id>
      <type>speech</type>
      <duration>20</duration>
      <needs>bureau</needs>
      <speaking>1564,8629,7912</speaking>
      <extra>
        <ddr>
          <checked>false</checked>
          <sources>Indiquer ici le détail des médias à diffuser.</sources>
        </ddr>
        <scroll>
          <checked>false</checked>
          <message>Indiquer ici le message à faire défiler (numéro de téléphone, consigne de sécurité, appel à l’action, etc.).</message>
        </scroll>
        <requests>
          <checked>false</checked>
          <specifications>Préciser ici vos besoins techniques spécifiques.</specifications>
        </requests>
      </extra>
    </SQ13>
    <SQ14>
      <id>0825</id>
      <type>transition</type>
      <html><![CDATA[<h1>Parcours et expériences variées de la pénalité :<br><br>Parcours carcéraux de mineurs et jeunes majeurs : l’épreuve de la majorité</h1>]]></html>
    </SQ14>
    <SQ15>
      <id>2216</id>
      <type>speech</type>
      <duration>20</duration>
      <needs>bureau</needs>
      <speaking>1564,8879,3335</speaking>
      <extra>
        <ddr>
          <checked>false</checked>
          <sources>Indiquer ici le détail des médias à diffuser.</sources>
        </ddr>
        <scroll>
          <checked>false</checked>
          <message>Indiquer ici le message à faire défiler (numéro de téléphone, consigne de sécurité, appel à l’action, etc.).</message>
        </scroll>
        <requests>
          <checked>false</checked>
          <specifications>Préciser ici vos besoins techniques spécifiques.</specifications>
        </requests>
      </extra>
    </SQ15>
    <SQ16>
      <id>4708</id>
      <type>transition</type>
      <html><![CDATA[<h1>Parcours et expériences variées de la pénalité :<br><br>« Avoir le mental » en prison :<br>des stratégies d’adaptation contrastées<br>selon le parcours des mineurs détenus</h1>]]></html>
    </SQ16>
    <SQ17>
      <id>6745</id>
      <type>speech</type>
      <duration>35</duration>
      <needs>bureau</needs>
      <speaking>1564,5236</speaking>
      <extra>
        <ddr>
          <checked>false</checked>
          <sources>Indiquer ici le détail des médias à diffuser.</sources>
        </ddr>
        <scroll>
          <checked>false</checked>
          <message>Indiquer ici le message à faire défiler (numéro de téléphone, consigne de sécurité, appel à l’action, etc.).</message>
        </scroll>
        <requests>
          <checked>false</checked>
          <specifications>Préciser ici vos besoins techniques spécifiques.</specifications>
        </requests>
      </extra>
    </SQ17>
    <SQ18>
      <id>4844</id>
      <type>pause</type>
      <duration>90</duration>
    </SQ18>
    <SQ19>
      <id>9786</id>
      <type>transition</type>
      <html><![CDATA[<h1>Conférence :<br><br>Les parcours de vie des jeunes :<br> processus et normes sociales</h1>]]></html>
    </SQ19>
    <SQ20>
      <id>5462</id>
      <type>speech</type>
      <duration>60</duration>
      <needs/>
      <speaking>2826,4600</speaking>
      <extra>
        <ddr>
          <checked>false</checked>
          <sources>Indiquer ici le détail des médias à diffuser.</sources>
        </ddr>
        <scroll>
          <checked>false</checked>
          <message>Indiquer ici le message à faire défiler (numéro de téléphone, consigne de sécurité, appel à l’action, etc.).</message>
        </scroll>
        <requests>
          <checked>false</checked>
          <specifications>Préciser ici vos besoins techniques spécifiques.</specifications>
        </requests>
      </extra>
    </SQ20>
  </sequence>
</fiche>
