<?xml version="1.0" encoding="UTF-8"?>
<fiche>
  <video>
    <title>A quoi servent les observatoires ?</title>
    <visibility>unlisted</visibility>
    <date>2024-10-09</date>
    <description>Description de la vidéo...</description>
  </video>
  <event>
    <title>A quoi servent les observatoires ?</title>
    <subtitle>Bienvenue</subtitle>
    <style>enpjj</style>
    <location>Amphi Costa</location>
    <onsite>25</onsite>
    <remote>60</remote>
    <release>Synchrone</release>
    <date>2024-10-09</date>
    <start>09:30</start>
  </event>
  <speaker>
    <SP1>
      <id>3553</id>
      <name>Fabien BEYRIA</name>
      <function><![CDATA[Directeur général de l'ENPJJ]]></function>
      <translation/>
      <attendance>onsite</attendance>
      <link>Copier/coller le lien ici...</link>
    </SP1>
    <SP2>
      <id>9953</id>
      <name>Agnès GINDT-DUCROS</name>
      <function>Directrice du service de la recherche et de la documentation (SRD), ENPJJ</function>
      <translation/>
      <attendance>onsite</attendance>
      <link>Copier/coller le lien ici...</link>
    </SP2>
    <SP3>
      <id>6101</id>
      <name>Delphine BRUGGEMAN</name>
      <function><![CDATA[Responsable de l'unité recherche et études (URE), responsable de l'Observatoire de la formation, ENPJJ]]></function>
      <translation/>
      <attendance>onsite</attendance>
      <link>Copier/coller le lien ici...</link>
    </SP3>
    <SP4>
      <id>6764</id>
      <name>Laurent GRAS</name>
      <function><![CDATA[Sociologue-démographe, responsable de l'Observatoire de la formation, Ecole nationale d'administration pénitentiaire (ENAP)]]></function>
      <translation/>
      <attendance>onsite</attendance>
      <link>Copier/coller le lien ici...</link>
    </SP4>
    <SP5>
      <id>1799</id>
      <name>Coralie ARANDA</name>
      <function><![CDATA[Chargée d'études, Observatoire départemental de la protection de l'enfance (ODPE)]]></function>
      <translation/>
      <attendance>onsite</attendance>
      <link>Copier/coller le lien ici...</link>
    </SP5>
    <SP6>
      <id>4906</id>
      <name>Thibault DELFAVERO</name>
      <function><![CDATA[Chargé d'études, Observatoire de la formation, ENPJJ]]></function>
      <translation/>
      <attendance>onsite</attendance>
      <link>Copier/coller le lien ici...</link>
    </SP6>
    <SP7>
      <id>8134</id>
      <name>Stéphane BERTOLINO</name>
      <function><![CDATA[Directeur de l'Observatoire de la direction des formations (ODiF), Université de Lille]]></function>
      <translation/>
      <attendance>onsite</attendance>
      <link>Copier/coller le lien ici...</link>
    </SP7>
    <SP8>
      <id>1474</id>
      <name>Anne OUI</name>
      <function><![CDATA[Chargée de mission, Observatoire national de la protection de l'enfance (ONPE)]]></function>
      <translation/>
      <attendance>onsite</attendance>
      <link>Copier/coller le lien ici...</link>
    </SP8>
    <SP9>
      <id>8582</id>
      <name>Caroline TOURAUT</name>
      <function><![CDATA[Chargée d'études, Observatoire nationale de protection de l'enfance (ONPE)]]></function>
      <translation/>
      <attendance>onsite</attendance>
      <link>Copier/coller le lien ici...</link>
    </SP9>
    <SP10>
      <id>4824</id>
      <name>Cécilia LAGARDE</name>
      <function><![CDATA[Chargée d'études, Ecole nationale d'administration pénitentiaire (ENAP)]]></function>
      <translation/>
      <attendance>onsite</attendance>
      <link>Copier/coller le lien ici...</link>
    </SP10>
    <SP11>
      <id>5462</id>
      <name>Joaquim TIMOTEO</name>
      <function><![CDATA[Chef de la mission études et recherche, Institut national de la jeunesse et de l'éducation populaire (INJEP)]]></function>
      <translation/>
      <attendance>onsite</attendance>
      <link>Copier/coller le lien ici...</link>
    </SP11>
    <SP12>
      <id>5989</id>
      <name>Marie FROUIN</name>
      <function><![CDATA[Chargée d'études, Observatoire de la formation, ENPJJ]]></function>
      <translation/>
      <attendance>onsite</attendance>
      <link>Copier/coller le lien ici...</link>
    </SP12>
  </speaker>
  <sequence>
    <SQ1>
      <id>2230</id>
      <type>transition</type>
      <html><![CDATA[<h2>Ouverture institutionnelle</h2><h1>et présentation de la journée</h1>]]></html>
    </SQ1>
    <SQ2>
      <id>6225</id>
      <type>speech</type>
      <duration>30</duration>
      <needs>bureau</needs>
      <speaking>6101,9953,3553</speaking>
      <extra>
        <ddr>
          <checked>false</checked>
          <sources>Indiquer ici le détail des médias à diffuser.</sources>
        </ddr>
        <scroll>
          <checked>false</checked>
          <message>Indiquer ici le message à faire défiler (numéro de téléphone, consigne de sécurité, appel à l’action, etc.).</message>
        </scroll>
        <requests>
          <checked>false</checked>
          <specifications>Préciser ici vos besoins techniques spécifiques.</specifications>
        </requests>
      </extra>
    </SQ2>
    <SQ3>
      <id>4736</id>
      <type>transition</type>
      <html><![CDATA[<h1>Conférence</h1><h2>L'observatoire de la formation<br>à l'ENAP : la parole est aux élèves</h2>]]></html>
    </SQ3>
    <SQ4>
      <id>5949</id>
      <type>speech</type>
      <duration>45</duration>
      <needs>bureau,pc</needs>
      <speaking>5989,6764</speaking>
      <extra>
        <ddr>
          <checked>false</checked>
          <sources>Indiquer ici le détail des médias à diffuser.</sources>
        </ddr>
        <scroll>
          <checked>false</checked>
          <message>Indiquer ici le message à faire défiler (numéro de téléphone, consigne de sécurité, appel à l’action, etc.).</message>
        </scroll>
        <requests>
          <checked>false</checked>
          <specifications>Préciser ici vos besoins techniques spécifiques.</specifications>
        </requests>
      </extra>
    </SQ4>
    <SQ5>
      <id>0433</id>
      <type>transition</type>
      <html><![CDATA[<h1>Echanges avec la salle</h1>]]></html>
    </SQ5>
    <SQ6>
      <id>5306</id>
      <type>speech</type>
      <duration>15</duration>
      <needs>bureau,hf</needs>
      <speaking>5989,6764</speaking>
      <extra>
        <ddr>
          <checked>false</checked>
          <sources>Indiquer ici le détail des médias à diffuser.</sources>
        </ddr>
        <scroll>
          <checked>false</checked>
          <message>Indiquer ici le message à faire défiler (numéro de téléphone, consigne de sécurité, appel à l’action, etc.).</message>
        </scroll>
        <requests>
          <checked>false</checked>
          <specifications>Préciser ici vos besoins techniques spécifiques.</specifications>
        </requests>
      </extra>
    </SQ6>
    <SQ7>
      <id>5057</id>
      <type>pause</type>
      <duration>15</duration>
    </SQ7>
    <SQ8>
      <id>8980</id>
      <type>transition</type>
      <html><![CDATA[<h1>Table ronde</h1><h2>Missions des observatoires, conditions et méthodes<br>de production des donnes</h2>]]></html>
    </SQ8>
    <SQ9>
      <id>2910</id>
      <type>speech</type>
      <duration>60</duration>
      <needs>bureau</needs>
      <speaking>6101,8134,4906,1799</speaking>
      <extra>
        <ddr>
          <checked>false</checked>
          <sources>Indiquer ici le détail des médias à diffuser.</sources>
        </ddr>
        <scroll>
          <checked>false</checked>
          <message>Indiquer ici le message à faire défiler (numéro de téléphone, consigne de sécurité, appel à l’action, etc.).</message>
        </scroll>
        <requests>
          <checked>false</checked>
          <specifications>Préciser ici vos besoins techniques spécifiques.</specifications>
        </requests>
      </extra>
    </SQ9>
    <SQ10>
      <id>2007</id>
      <type>transition</type>
      <html><![CDATA[<h1>Echanges avec la salle</h1>]]></html>
    </SQ10>
    <SQ11>
      <id>0450</id>
      <type>speech</type>
      <duration>15</duration>
      <needs>bureau,hf</needs>
      <speaking>6101,8134,4906,1799</speaking>
      <extra>
        <ddr>
          <checked>false</checked>
          <sources>Indiquer ici le détail des médias à diffuser.</sources>
        </ddr>
        <scroll>
          <checked>false</checked>
          <message>Indiquer ici le message à faire défiler (numéro de téléphone, consigne de sécurité, appel à l’action, etc.).</message>
        </scroll>
        <requests>
          <checked>false</checked>
          <specifications>Préciser ici vos besoins techniques spécifiques.</specifications>
        </requests>
      </extra>
    </SQ11>
    <SQ12>
      <id>3504</id>
      <type>pause</type>
      <duration>90</duration>
    </SQ12>
    <SQ13>
      <id>4805</id>
      <type>transition</type>
      <html><![CDATA[<h1>Conférence</h1><h2>Faire de la recherche au service<br>de la pratique : défis et leviers </h2>]]></html>
    </SQ13>
    <SQ14>
      <id>5264</id>
      <type>speech</type>
      <duration>45</duration>
      <needs>bureau</needs>
      <speaking>5989,8582,1474</speaking>
      <extra>
        <ddr>
          <checked>false</checked>
          <sources>Indiquer ici le détail des médias à diffuser.</sources>
        </ddr>
        <scroll>
          <checked>false</checked>
          <message>Indiquer ici le message à faire défiler (numéro de téléphone, consigne de sécurité, appel à l’action, etc.).</message>
        </scroll>
        <requests>
          <checked>false</checked>
          <specifications>Préciser ici vos besoins techniques spécifiques.</specifications>
        </requests>
      </extra>
    </SQ14>
    <SQ15>
      <id>4305</id>
      <type>transition</type>
      <html><![CDATA[<h1>Echanges avec la salle</h1>]]></html>
    </SQ15>
    <SQ16>
      <id>5555</id>
      <type>speech</type>
      <duration>15</duration>
      <needs>bureau,hf</needs>
      <speaking>5989,8582,1474</speaking>
      <extra>
        <ddr>
          <checked>false</checked>
          <sources>Indiquer ici le détail des médias à diffuser.</sources>
        </ddr>
        <scroll>
          <checked>false</checked>
          <message>Indiquer ici le message à faire défiler (numéro de téléphone, consigne de sécurité, appel à l’action, etc.).</message>
        </scroll>
        <requests>
          <checked>false</checked>
          <specifications>Préciser ici vos besoins techniques spécifiques.</specifications>
        </requests>
      </extra>
    </SQ16>
    <SQ17>
      <id>2448</id>
      <type>transition</type>
      <html><![CDATA[<h1>Table ronde</h1><h2>stratégies de valorisation<br>et de diffusion :<br>pour quels objectifs<br>et quels publics ?</h2>]]></html>
    </SQ17>
    <SQ18>
      <id>2191</id>
      <type>speech</type>
      <duration>60</duration>
      <needs>bureau</needs>
      <speaking>4906,5462,4824,8582</speaking>
      <extra>
        <ddr>
          <checked>false</checked>
          <sources>Indiquer ici le détail des médias à diffuser.</sources>
        </ddr>
        <scroll>
          <checked>false</checked>
          <message>Indiquer ici le message à faire défiler (numéro de téléphone, consigne de sécurité, appel à l’action, etc.).</message>
        </scroll>
        <requests>
          <checked>false</checked>
          <specifications>Préciser ici vos besoins techniques spécifiques.</specifications>
        </requests>
      </extra>
    </SQ18>
    <SQ19>
      <id>8773</id>
      <type>transition</type>
      <html><![CDATA[<h1>Echanges avec la salle</h1>]]></html>
    </SQ19>
    <SQ20>
      <id>9788</id>
      <type>speech</type>
      <duration>15</duration>
      <needs>bureau,hf</needs>
      <speaking>4906,5462,4824,8582</speaking>
      <extra>
        <ddr>
          <checked>false</checked>
          <sources>Indiquer ici le détail des médias à diffuser.</sources>
        </ddr>
        <scroll>
          <checked>false</checked>
          <message>Indiquer ici le message à faire défiler (numéro de téléphone, consigne de sécurité, appel à l’action, etc.).</message>
        </scroll>
        <requests>
          <checked>false</checked>
          <specifications>Préciser ici vos besoins techniques spécifiques.</specifications>
        </requests>
      </extra>
    </SQ20>
    <SQ21>
      <id>8477</id>
      <type>transition</type>
      <html><![CDATA[<h2>Le regard du "grand témoin"</h2>]]></html>
    </SQ21>
    <SQ22>
      <id>3692</id>
      <type>speech</type>
      <duration>30</duration>
      <needs>bureau</needs>
      <speaking>9953</speaking>
      <extra>
        <ddr>
          <checked>false</checked>
          <sources>Indiquer ici le détail des médias à diffuser.</sources>
        </ddr>
        <scroll>
          <checked>false</checked>
          <message>Indiquer ici le message à faire défiler (numéro de téléphone, consigne de sécurité, appel à l’action, etc.).</message>
        </scroll>
        <requests>
          <checked>false</checked>
          <specifications>Préciser ici vos besoins techniques spécifiques.</specifications>
        </requests>
      </extra>
    </SQ22>
    <SQ23>
      <id>5859</id>
      <type>transition</type>
      <html><![CDATA[<h1>Conclusions</h1>]]></html>
    </SQ23>
    <SQ24>
      <id>6242</id>
      <type>speech</type>
      <duration>15</duration>
      <needs>bureau</needs>
      <speaking>5989,4906</speaking>
      <extra>
        <ddr>
          <checked>false</checked>
          <sources>Indiquer ici le détail des médias à diffuser.</sources>
        </ddr>
        <scroll>
          <checked>false</checked>
          <message>Indiquer ici le message à faire défiler (numéro de téléphone, consigne de sécurité, appel à l’action, etc.).</message>
        </scroll>
        <requests>
          <checked>false</checked>
          <specifications>Préciser ici vos besoins techniques spécifiques.</specifications>
        </requests>
      </extra>
    </SQ24>
  </sequence>
</fiche>
