<?xml version="1.0" encoding="UTF-8"?>
<fiche>
  <video>
    <title><![CDATA[L’eau, les eaux et la justice ? | Colloque de l'AFMJE 1/3]]></title>
    <visibility>unlisted</visibility>
    <date>2024-12-06</date>
    <description><![CDATA[L’eau désigne un fluide très commun, qui ne posait jusqu’alors que peu de questions, du moins aux habitants des pays tempérés.<br><br>La diminution de la ressource en eau, associée aux changements climatiques, à la sécheresse, aux incendies de forêt, à la raréfaction de l’eau potable, interroge désormais fortement la société civile, les opérateurs économiques, mais aussi les juristes, dont les juges et les procureurs.<br><br>Pour ces derniers, le sujet de l’eau devient … celui des eaux, en ce qu’il convoque des statuts juridiques différents : les eaux de mer, les eaux douces, les eaux de source, les eaux souterraines, les eaux usées, les eaux polluées, les eaux potables, les eaux toxiques, notamment.<br><br>A la lumière de perspectives économiques, sociologiques, philosophiques, complémentaires au droit, ce colloque permettra des échanges entre professionnels de différents horizons, magistrats, avocats, responsables associatifs, opérateurs économiques, élus et fonctionnaires.<br><br>Il mettra en lumière l’articulation entre les besoins en eau, variés, les évolutions possibles de son statut, notamment sous l’angle du droit de propriété, qui interroge la notion « d’eau bien commun », des liens entre l’eau et la santé, de la prévention des risques, de l’action de la justice civile et pénale, dont la réparation des préjudices.<br><br>C’est aussi, il faut en avoir conscience, un sujet qui interroge la situation sécuritaire de la planète, l’eau étant indispensable à la survie des espèces et des végétaux.<br><br>Accueilli cette année en province, à Roubaix, dans l’une des écoles du Ministère de la Justice, l’École Nationale de Protection Judiciaire de la Jeunesse, dont nous remercions très vivement l’équipe pour son accueil enthousiaste, notre colloque a aussi vocation à offrir une perspective aux générations futures.]]></description>
  </video>
  <event>
    <title><![CDATA[Colloque annuel de l'AFMJE]]></title>
    <subtitle>L’eau, les eaux et la justice ?</subtitle>
    <style>afmje</style>
    <location>Amphi Condorcet Bas</location>
    <onsite>130</onsite>
    <remote>120</remote>
    <release>Synchrone</release>
    <date>2024-12-06</date>
    <start>15:30</start>
  </event>
  <speaker>
    <SP1>
      <id>2982</id>
      <name>Caroline NISAND</name>
      <function>Directrice de la Protection Judiciaire de la Jeunesse</function>
      <translation/>
      <attendance>onsite</attendance>
      <link>Copier/coller le lien ici...</link>
    </SP1>
    <SP2>
      <id>3831</id>
      <name>Rémy HEITZ</name>
      <function>Procureur général près la Cour de cassation</function>
      <translation/>
      <attendance>onsite</attendance>
      <link>Copier/coller le lien ici...</link>
    </SP2>
    <SP3>
      <id>7884</id>
      <name>Charles FOURMAUX</name>
      <function><![CDATA[Directeur de la police et du permis de chasser<br>Office Français de la Biodiversité – OFB]]></function>
      <translation/>
      <attendance>onsite</attendance>
      <link>Copier/coller le lien ici...</link>
    </SP3>
    <SP4>
      <id>5601</id>
      <name>Général de division Sylvain NOYAU</name>
      <function><![CDATA[Commandant du CESAN – Commandement pour l’environnement<br>et la santé de la Gendarmerie Nationale]]></function>
      <translation/>
      <attendance>onsite</attendance>
      <link>Copier/coller le lien ici...</link>
    </SP4>
    <SP5>
      <id>3264</id>
      <name>Luc LAVRYSEN</name>
      <function><![CDATA[Président de la Cour constitutionnelle de Belgique<br>Professeur émérite en droit de l’environnement de l’Université de Gand]]></function>
      <translation/>
      <attendance>onsite</attendance>
      <link>Copier/coller le lien ici...</link>
    </SP5>
    <SP6>
      <id>5550</id>
      <name>Jean-Philippe RIVAUD</name>
      <function><![CDATA[Magistrat - Parquet général près la Cour d’appel de Paris.<br>Cofondateur et président de l’AFMJE]]></function>
      <translation/>
      <attendance>onsite</attendance>
      <link>Copier/coller le lien ici...</link>
    </SP6>
    <SP7>
      <id>1428</id>
      <name>Bernard DROBENKO</name>
      <function>Professeur émérite de droit public</function>
      <translation/>
      <attendance>onsite</attendance>
      <link>Copier/coller le lien ici...</link>
    </SP7>
    <SP8>
      <id>6675</id>
      <name>Luc ABBADIE</name>
      <function><![CDATA[Professeur émérite d’écologie - Sorbonne Université<br>Vice-président du conseil scientifique de l’Office Français de la Biodiversité]]></function>
      <translation/>
      <attendance>onsite</attendance>
      <link>Copier/coller le lien ici...</link>
    </SP8>
    <SP9>
      <id>0328</id>
      <name>Xavier LEFLAIVE</name>
      <function><![CDATA[Administrateur principal<br>Spécialiste des politiques de l’eau<br>Organisation de Coopération et de Développement Économique (OCDE)]]></function>
      <translation/>
      <attendance>onsite</attendance>
      <link>Copier/coller le lien ici...</link>
    </SP9>
    <SP10>
      <id>9897</id>
      <name>Edgar MORIN</name>
      <function>Sociologue et philosophe</function>
      <translation/>
      <attendance>onsite</attendance>
      <link>Copier/coller le lien ici...</link>
    </SP10>
  </speaker>
  <sequence>
    <SQ1>
      <id>2762</id>
      <type>transition</type>
      <html><![CDATA[<h1> Propos d’ouverture</h1>]]></html>
    </SQ1>
    <SQ2>
      <id>9073</id>
      <type>speech</type>
      <duration>60</duration>
      <needs>pupitre</needs>
      <speaking>5550,3264,5601,7884,3831,2982</speaking>
      <extra>
        <ddr>
          <checked>true</checked>
          <sources>Un powerpoint avec le nom/prénom et fonction des intervenants.</sources>
        </ddr>
        <scroll>
          <checked>false</checked>
          <message>Indiquer ici le message à faire défiler (numéro de téléphone, consigne de sécurité, appel à l’action, etc.).</message>
        </scroll>
        <requests>
          <checked>true</checked>
          <specifications>Est-il possible de retirer le grand meuble beige pour la journée ?</specifications>
        </requests>
      </extra>
    </SQ2>
    <SQ3>
      <id>3422</id>
      <type>transition</type>
      <html><![CDATA[<h1>Quels enjeux juridiques<br>pour les eaux ?</h1> <br><i>Bernard DROBENKO</i>]]></html>
    </SQ3>
    <SQ4>
      <id>1582</id>
      <type>speech</type>
      <duration>30</duration>
      <needs>pupitre</needs>
      <speaking>1428</speaking>
      <extra>
        <ddr>
          <checked>false</checked>
          <sources>Indiquer ici le détail des médias à diffuser.</sources>
        </ddr>
        <scroll>
          <checked>false</checked>
          <message>Indiquer ici le message à faire défiler (numéro de téléphone, consigne de sécurité, appel à l’action, etc.).</message>
        </scroll>
        <requests>
          <checked>false</checked>
          <specifications>Préciser ici vos besoins techniques spécifiques.</specifications>
        </requests>
      </extra>
    </SQ4>
    <SQ5>
      <id>6594</id>
      <type>transition</type>
      <html><![CDATA[<h1>L’eau à l’ère de l’effondrement<br>de la biodiversité<br>et de la crise climatique</h1> <br><i> Luc ABBADIE </i>]]></html>
    </SQ5>
    <SQ6>
      <id>6114</id>
      <type>speech</type>
      <duration>30</duration>
      <needs>pupitre</needs>
      <speaking>6675</speaking>
      <extra>
        <ddr>
          <checked>false</checked>
          <sources>Indiquer ici le détail des médias à diffuser.</sources>
        </ddr>
        <scroll>
          <checked>false</checked>
          <message>Indiquer ici le message à faire défiler (numéro de téléphone, consigne de sécurité, appel à l’action, etc.).</message>
        </scroll>
        <requests>
          <checked>false</checked>
          <specifications>Préciser ici vos besoins techniques spécifiques.</specifications>
        </requests>
      </extra>
    </SQ6>
    <SQ7>
      <id>5492</id>
      <type>transition</type>
      <html><![CDATA[<h1>L’eau et le développement économique :<br>le point de vue de l’OCDE</h1> <br><i>Xavier LEFLAIVE</i>]]></html>
    </SQ7>
    <SQ8>
      <id>8019</id>
      <type>speech</type>
      <duration>30</duration>
      <needs>pupitre</needs>
      <speaking>0328</speaking>
      <extra>
        <ddr>
          <checked>false</checked>
          <sources>Indiquer ici le détail des médias à diffuser.</sources>
        </ddr>
        <scroll>
          <checked>false</checked>
          <message>Indiquer ici le message à faire défiler (numéro de téléphone, consigne de sécurité, appel à l’action, etc.).</message>
        </scroll>
        <requests>
          <checked>false</checked>
          <specifications>Préciser ici vos besoins techniques spécifiques.</specifications>
        </requests>
      </extra>
    </SQ8>
    <SQ9>
      <id>3331</id>
      <type>transition</type>
      <html><![CDATA[<h1>Le grand témoin</h2><br><i>Edgar MORIN</i>]]></html>
    </SQ9>
    <SQ10>
      <id>1236</id>
      <type>speech</type>
      <duration>30</duration>
      <needs>pupitre</needs>
      <speaking>9897</speaking>
      <extra>
        <ddr>
          <checked>true</checked>
          <sources>Une photographie à projeter pendant la prise de parole.</sources>
        </ddr>
        <scroll>
          <checked>false</checked>
          <message>Indiquer ici le message à faire défiler (numéro de téléphone, consigne de sécurité, appel à l’action, etc.).</message>
        </scroll>
        <requests>
          <checked>false</checked>
          <specifications>Préciser ici vos besoins techniques spécifiques.</specifications>
        </requests>
      </extra>
    </SQ10>
  </sequence>
</fiche>
